{
  "$schema": "https://mintlify.com/docs.json",
  "name": "Zayne Labs UI",
  "theme": "palm",
  "colors": {
    "primary": "#6366f1",
    "light": "#818cf8",
    "dark": "#4f46e5"
  },
  "navbar": {
    "primary": {
      "type": "github",
      "href": "https://github.com/zayne-labs/ui"
    }
  },
  "footer": {
    "socials": {
      "github": "https://github.com/zayne-labs/ui"
    }
  },
  "navigation": {
    "tabs": [
      {
        "tab": "Documentation",
        "groups": [
          {
            "group": "Getting Started",
            "pages": [
              "introduction",
              "installation",
              "quickstart"
            ]
          },
          {
            "group": "Core Concepts",
            "pages": [
              "concepts/component-structure",
              "concepts/styling",
              "concepts/typescript"
            ]
          },
          {
            "group": "UI Components",
            "pages": [
              "components/ui/card",
              "components/ui/carousel",
              "components/ui/drag-scroll",
              "components/ui/drop-zone",
              "components/ui/form"
            ]
          },
          {
            "group": "Utility Components",
            "pages": [
              "components/utility/await",
              "components/utility/client-gate",
              "components/utility/error-boundary",
              "components/utility/for",
              "components/utility/presence",
              "components/utility/show",
              "components/utility/slot",
              "components/utility/suspense-with-boundary",
              "components/utility/switch",
              "components/utility/teleport"
            ]
          }
        ]
      },
      {
        "tab": "API Reference",
        "groups": [
          {
            "group": "UI Components",
            "pages": [
              "api/ui/card",
              "api/ui/carousel",
              "api/ui/drag-scroll",
              "api/ui/drop-zone",
              "api/ui/form"
            ]
          },
          {
            "group": "Utility Components",
            "pages": [
              "api/utility/await",
              "api/utility/client-gate",
              "api/utility/error-boundary",
              "api/utility/for",
              "api/utility/presence",
              "api/utility/show",
              "api/utility/slot",
              "api/utility/suspense-with-boundary",
              "api/utility/switch",
              "api/utility/teleport"
            ]
          }
        ]
      }
    ]
  }
}
